{
    "entities":
    [
        {
            "manufacturer": "Porsche",
            "model": "911",
            "price": 135000,
            "year": "2015",
            "img": "911"
        },
        {
            "manufacturer": "Nissan",
            "model": "GT-R",
            "price": 120000,
            "year": "2015",
            "img": "GT-R"
        },
        {
            "manufacturer": "BMW",
            "model": "M3",
            "price": 70500,
            "year": "2014",
            "img": "M3"
        },
        {
            "manufacturer": "Audi",
            "model": "TT",
            "price": 40000,
            "year": "2012",
            "img": "TT"
        },
        {
            "manufacturer": "BMW",
            "model": "M2",
            "price": 65000,
            "year": "2020",
            "img": "M2"
        }
    ]
}
